README.rst
setup.py
orangeapisms/__init__.py
orangeapisms/admin.py
orangeapisms/config.py
orangeapisms/datetime.py
orangeapisms/dj_settings_tests.py
orangeapisms/exceptions.py
orangeapisms/models.py
orangeapisms/stub.py
orangeapisms/tests.py
orangeapisms/urls.py
orangeapisms/utils.py
orangeapisms/views.py
orangeapisms.egg-info/PKG-INFO
orangeapisms.egg-info/SOURCES.txt
orangeapisms.egg-info/dependency_links.txt
orangeapisms.egg-info/not-zip-safe
orangeapisms.egg-info/requires.txt
orangeapisms.egg-info/top_level.txt
orangeapisms/migrations/0001_initial.py
orangeapisms/migrations/__init__.py
orangeapisms/templates/orangeapisms/base.html
orangeapisms/templates/orangeapisms/home.html
orangeapisms/templates/orangeapisms/paginator.html
orangeapisms/templates/orangeapisms/tester_form.html
orangeapisms/templates/orangeapisms/tester_logs.html