Metadata-Version: 1.1
Name: orangeapisms
Version: 0.28
Summary: Django app to add support for Orange API SMS-MO, SMS-MT/DR
Home-page: http://github.com/rgaudin/django-orangeapisms
Author: renaud gaudin
Author-email: rgaudin@gmail.com
License: Public Domain
Keywords: orange api sms
Platform: any
Classifier: Development Status :: 4 - Beta
Classifier: Intended Audience :: Developers
Classifier: License :: Public Domain
Classifier: License :: CC0 1.0 Universal (CC0 1.0) Public Domain Dedication
Classifier: Programming Language :: Python
Classifier: Programming Language :: Python :: 2.7
Classifier: Programming Language :: Python :: 3.5
